fahad_server/__init__.py
fahad_server/server.py
fahad_mcp_server-0.1.5.dist-info/METADATA
fahad_mcp_server-0.1.5.dist-info/WHEEL
fahad_mcp_server-0.1.5.dist-info/entry_points.txt
fahad_mcp_server-0.1.5.dist-info/top_level.txt
fahad_mcp_server-0.1.5.dist-info/RECORD
