Metadata-Version: 2.4
Name: fahad-mcp-server
Version: 0.1.5
Summary: An MCP server for integrating with X system.
Author: Fahad Khan
Author-email: khan.fahad855@gmail.com
Classifier: Programming Language :: Python :: 3
Classifier: License :: OSI Approved :: MIT License
Classifier: Operating System :: OS Independent
Requires-Dist: mcp
Dynamic: author
Dynamic: author-email
Dynamic: classifier
Dynamic: description
Dynamic: description-content-type
Dynamic: requires-dist
Dynamic: summary
